chatscope/__init__.py
chatscope/analyzer.py
chatscope/cli.py
chatscope/exceptions.py
chatscope-1.0.2.dist-info/METADATA
chatscope-1.0.2.dist-info/WHEEL
chatscope-1.0.2.dist-info/entry_points.txt
chatscope-1.0.2.dist-info/top_level.txt
chatscope-1.0.2.dist-info/RECORD
