Metadata-Version: 2.4
Name: chatscope
Version: 1.0.2
Summary: Analyze and categorize ChatGPT conversation exports using OpenAI API
Author-email: 22wojciech <plus4822@icloud.com>
License: Custom Non-Commercial License (CNCL) v1.0
Project-URL: Homepage, https://github.com/22wojciech/chatscope
Project-URL: Bug Reports, https://github.com/22wojciech/chatscope/issues
Project-URL: Source, https://github.com/22wojciech/chatscope
Project-URL: Documentation, https://github.com/22wojciech/chatscope#readme
Keywords: chatgpt,openai,conversation,analysis,categorization,nlp
Classifier: Development Status :: 4 - Beta
Classifier: Intended Audience :: Developers
Classifier: Intended Audience :: End Users/Desktop
Classifier: License :: Other/Proprietary License
Classifier: Operating System :: OS Independent
Classifier: Programming Language :: Python :: 3
Classifier: Programming Language :: Python :: 3.8
Classifier: Programming Language :: Python :: 3.9
Classifier: Programming Language :: Python :: 3.10
Classifier: Programming Language :: Python :: 3.11
Classifier: Topic :: Scientific/Engineering :: Artificial Intelligence
Classifier: Topic :: Text Processing :: Linguistic
Classifier: Topic :: Utilities
Requires-Python: >=3.8
Requires-Dist: openai<1.0.0,>=0.28.0
Requires-Dist: python-dotenv>=0.19.0
Requires-Dist: requests>=2.25.0
Provides-Extra: plotting
Requires-Dist: matplotlib>=3.5.0; extra == "plotting"
Provides-Extra: dev
Requires-Dist: pytest>=6.0; extra == "dev"
Requires-Dist: pytest-cov>=2.0; extra == "dev"
Requires-Dist: black>=21.0; extra == "dev"
Requires-Dist: flake8>=3.8; extra == "dev"
Requires-Dist: mypy>=0.800; extra == "dev"
Requires-Dist: matplotlib>=3.5.0; extra == "dev"
Provides-Extra: all
Requires-Dist: matplotlib>=3.5.0; extra == "all"
